ardu_report_lib-1.0.2.dist-info/DESCRIPTION.rst
ardu_report_lib-1.0.2.dist-info/METADATA
ardu_report_lib-1.0.2.dist-info/RECORD
ardu_report_lib-1.0.2.dist-info/WHEEL
ardu_report_lib-1.0.2.dist-info/metadata.json
ardu_report_lib-1.0.2.dist-info/top_level.txt
libardurep/__init__.py
libardurep/datareporter.py
libardurep/datastore.py
libardurep/serialreader.py
