Metadata-Version: 2.0
Name: ardu-report-lib
Version: 1.0.2
Summary: Get sensor data over the serial line and send it to an URL (JSON).
Home-page: https://github.com/zwischenloesung/ardu-report-lib
Author: Michael Lustenberger
Author-email: mic@inofix.ch
License: GPLv3
Keywords: arduino sensor json
Platform: UNKNOWN
Classifier: Development Status :: 5 - Production/Stable
Classifier: Intended Audience :: Developers
Classifier: Topic :: Scientific/Engineering
Classifier: Topic :: Internet
Classifier: Topic :: Software Development :: Libraries :: Python Modules
Classifier: License :: OSI Approved :: GNU General Public License (GPL)
Classifier: Programming Language :: Python :: 2
Classifier: Programming Language :: Python :: 2.7
Classifier: Programming Language :: Python :: 3
Classifier: Programming Language :: Python :: 3.3
Classifier: Programming Language :: Python :: 3.4
Classifier: Programming Language :: Python :: 3.5
Requires-Dist: jsonschema
Requires-Dist: pyserial
Requires-Dist: requests
